<?xml version="1.0" encoding="utf-8" ?>
<rsp>
  <user>
    <user_id>65753281</user_id>
    <created>2008-03-09 02:19:35</created>
    <location>
      <city><![CDATA[杭州]]></city>
      <state><![CDATA[浙江]]></state>
    </location>
    <nick><![CDATA[tbtest520]]></nick>
    <sex><![CDATA[m]]></sex>
  </user>
  <user>
    <user_id>175754639</user_id>
    <created>2008-03-09 02:27:01</created>
    <location>
      <city><![CDATA[北京]]></city>
      <country><![CDATA[中国]]></country>
      <state><![CDATA[北京]]></state>
    </location>
    <nick><![CDATA[tbtest562]]></nick>
    <sex><![CDATA[m]]></sex>
  </user>
</rsp>
<!--xvm176.sqa-->